LICENSE
MANIFEST.in
README.md
requirements.txt
setup.cfg
setup.py
askdata_api_python_client/__init__.py
askdata_api_python_client/askdata.py
askdata_api_python_client/catalog.py
askdata_api_python_client/channel.py
askdata_api_python_client/dataset.py
askdata_api_python_client/insight.py
askdata_api_python_client.egg-info/PKG-INFO
askdata_api_python_client.egg-info/SOURCES.txt
askdata_api_python_client.egg-info/dependency_links.txt
askdata_api_python_client.egg-info/not-zip-safe
askdata_api_python_client.egg-info/requires.txt
askdata_api_python_client.egg-info/top_level.txt
askdata_api_python_client/askdata_config/base_url.yaml