Metadata-Version: 2.1
Name: askdata-api-python-client
Version: 0.2.31
Summary: A library for creating a client for interacting with Askdata
Home-page: https://github.com/AskdataInc/askdata-api-python-client
Author: ['Giuseppe De Maio', 'Matteo Giacalone']
Author-email: datascience@askdata.com
License: Apache License 2.0
Keywords: nlp
Platform: UNKNOWN
Classifier: Programming Language :: Python :: 3
Classifier: Operating System :: OS Independent
Classifier: License :: OSI Approved :: MIT License
Classifier: Development Status :: 3 - Alpha
Requires-Python: >=3, <4
